etdot/__init__.py
etdot/cpp_dotc/CMakeLists.txt
etdot/cpp_dotc/dotc.cpp
etdot/cpp_dotc/dotc.rst
etdot/f90_dotf/CMakeLists.txt
etdot/f90_dotf/dotf.f90
etdot/f90_dotf/dotf.rst
etdot-1.3.0.dist-info/entry_points.txt
etdot-1.3.0.dist-info/LICENSE
etdot-1.3.0.dist-info/WHEEL
etdot-1.3.0.dist-info/METADATA
etdot-1.3.0.dist-info/RECORD
