Metadata-Version: 2.1
Name: etdot
Version: 1.3.0
Summary: <Enter a one-sentence description of this project here.>
Home-page: https://github.com/etijskens/etDot
License: MIT
Keywords: packaging,poetry
Author: Bert Tijskens
Author-email: engelbert.tijskens@uantwerpen.be
Requires-Python: >=3.7,<4.0
Classifier: License :: OSI Approved :: MIT License
Classifier: Programming Language :: Python :: 3
Classifier: Programming Language :: Python :: 3.7
Classifier: Programming Language :: Python :: 3.8
Classifier: Programming Language :: Python :: 3.9
Requires-Dist: et-micc-build (>=1.1.3,<2.0.0)
Requires-Dist: numpy (>=1.20.1,<2.0.0)
Project-URL: Repository, https://github.com/etijskens/etDot
